{"collaborators_url": "https://api.github.com/repos/ikew0ng/Blog/collaborators{/collaborator}", "keys_url": "https://api.github.com/repos/ikew0ng/Blog/keys{/key_id}", "open_issues": 2, "has_pages": false, "deployments_url": "https://api.github.com/repos/ikew0ng/Blog/deployments", "stargazers_url": "https://api.github.com/repos/ikew0ng/Blog/stargazers", "events_url": "https://api.github.com/repos/ikew0ng/Blog/events", "comments_url": "https://api.github.com/repos/ikew0ng/Blog/comments{/number}", "watchers": 0, "created_at": "2013-07-21T13:27:04Z", "open_issues_count": 2, "milestones_url": "https://api.github.com/repos/ikew0ng/Blog/milestones{/number}", "full_name": "ikew0ng/Blog", "pulls_url": "https://api.github.com/repos/ikew0ng/Blog/pulls{/number}", "default_branch": "master", "compare_url": "https://api.github.com/repos/ikew0ng/Blog/compare/{base}...{head}", "url": "https://api.github.com/repos/ikew0ng/Blog", "merges_url": "https://api.github.com/repos/ikew0ng/Blog/merges", "git_refs_url": "https://api.github.com/repos/ikew0ng/Blog/git/refs{/sha}", "stargazers_count": 0, "issue_comment_url": "https://api.github.com/repos/ikew0ng/Blog/issues/comments{/number}", "pushed_at": "2013-11-13T18:14:04Z", "downloads_url": "https://api.github.com/repos/ikew0ng/Blog/downloads", "subscribers_url": "https://api.github.com/repos/ikew0ng/Blog/subscribers", "releases_url": "https://api.github.com/repos/ikew0ng/Blog/releases{/id}", "forks": 5, "permissions": {"pull": true, "admin": false, "push": false}, "mirror_url": null, "size": 11345, "git_commits_url": "https://api.github.com/repos/ikew0ng/Blog/git/commits{/sha}", "forks_url": "https://api.github.com/repos/ikew0ng/Blog/forks", "languages_url": "https://api.github.com/repos/ikew0ng/Blog/languages", "watchers_count": 0, "branches_url": "https://api.github.com/repos/ikew0ng/Blog/branches{/branch}", "id": 11562006, "contents_url": "https://api.github.com/repos/ikew0ng/Blog/contents/{+path}", "subscribers_count": 1, "issues_url": "https://api.github.com/repos/ikew0ng/Blog/issues{/number}", "has_issues": true, "network_count": 5, "name": "Blog", "description": "My Blog", "trees_url": "https://api.github.com/repos/ikew0ng/Blog/git/trees{/sha}", "commits_url": "https://api.github.com/repos/ikew0ng/Blog/commits{/sha}", "archive_url": "https://api.github.com/repos/ikew0ng/Blog/{archive_format}{/ref}", "updated_at": "2015-03-19T00:31:55Z", "forks_count": 5, "has_wiki": true, "labels_url": "https://api.github.com/repos/ikew0ng/Blog/labels{/name}", "blobs_url": "https://api.github.com/repos/ikew0ng/Blog/git/blobs{/sha}", "notifications_url": "https://api.github.com/repos/ikew0ng/Blog/notifications{?since,all,participating}", "issue_events_url": "https://api.github.com/repos/ikew0ng/Blog/issues/events{/number}", "owner": {"avatar_url": "https://avatars.githubusercontent.com/u/1014961?v=3", "url": "https://api.github.com/users/ikew0ng", "html_url": "https://github.com/ikew0ng", "gists_url": "https://api.github.com/users/ikew0ng/gists{/gist_id}", "organizations_url": "https://api.github.com/users/ikew0ng/orgs", "id": 1014961, "events_url": "https://api.github.com/users/ikew0ng/events{/privacy}", "subscriptions_url": "https://api.github.com/users/ikew0ng/subscriptions", "following_url": "https://api.github.com/users/ikew0ng/following{/other_user}", "login": "ikew0ng", "repos_url": "https://api.github.com/users/ikew0ng/repos", "type": "User", "site_admin": false, "gravatar_id": "", "received_events_url": "https://api.github.com/users/ikew0ng/received_events", "followers_url": "https://api.github.com/users/ikew0ng/followers", "starred_url": "https://api.github.com/users/ikew0ng/starred{/owner}{/repo}"}, "language": "Ruby", "has_downloads": true, "html_url": "https://github.com/ikew0ng/Blog", "fork": false, "ssh_url": "git@github.com:ikew0ng/Blog.git", "hooks_url": "https://api.github.com/repos/ikew0ng/Blog/hooks", "statuses_url": "https://api.github.com/repos/ikew0ng/Blog/statuses/{sha}", "git_tags_url": "https://api.github.com/repos/ikew0ng/Blog/git/tags{/sha}", "teams_url": "https://api.github.com/repos/ikew0ng/Blog/teams", "private": false, "git_url": "git://github.com/ikew0ng/Blog.git", "subscription_url": "https://api.github.com/repos/ikew0ng/Blog/subscription", "tags_url": "https://api.github.com/repos/ikew0ng/Blog/tags", "assignees_url": "https://api.github.com/repos/ikew0ng/Blog/assignees{/user}", "clone_url": "https://github.com/ikew0ng/Blog.git", "homepage": null, "svn_url": "https://github.com/ikew0ng/Blog", "contributors_url": "https://api.github.com/repos/ikew0ng/Blog/contributors"}